AUTHORS.rst
CHANGES.rst
LICENSE.txt
MANIFEST.in
README.rst
setup.cfg
setup.py
Flask_User_AWS.egg-info/PKG-INFO
Flask_User_AWS.egg-info/SOURCES.txt
Flask_User_AWS.egg-info/dependency_links.txt
Flask_User_AWS.egg-info/not-zip-safe
Flask_User_AWS.egg-info/requires.txt
Flask_User_AWS.egg-info/top_level.txt
flask_user/__init__.py
flask_user/db_manager.py
flask_user/decorators.py
flask_user/email_manager.py
flask_user/forms.py
flask_user/legacy_error.py
flask_user/password_manager.py
flask_user/signals.py
flask_user/token_manager.py
flask_user/translation_utils.py
flask_user/user_manager.py
flask_user/user_manager__settings.py
flask_user/user_manager__utils.py
flask_user/user_manager__views.py
flask_user/user_mixin.py
flask_user/db_adapters/__init__.py
flask_user/db_adapters/db_adapter_interface.py
flask_user/db_adapters/dynamo_db_adapter.py
flask_user/db_adapters/mongo_db_adapter.py
flask_user/db_adapters/pynamo_db_adapter.py
flask_user/db_adapters/sql_db_adapter.py
flask_user/email_adapters/__init__.py
flask_user/email_adapters/email_adapter_interface.py
flask_user/email_adapters/sendgrid_email_adapter.py
flask_user/email_adapters/sendmail_email_adapter.py
flask_user/email_adapters/smtp_email_adapter.py
flask_user/templates/flask_user_layout.html
flask_user/templates/flask_user/_authorized_base.html
flask_user/templates/flask_user/_common_base.html
flask_user/templates/flask_user/_macros.html
flask_user/templates/flask_user/_public_base.html
flask_user/templates/flask_user/change_password.html
flask_user/templates/flask_user/change_username.html
flask_user/templates/flask_user/edit_user_profile.html
flask_user/templates/flask_user/forgot_password.html
flask_user/templates/flask_user/invite_user.html
flask_user/templates/flask_user/login.html
flask_user/templates/flask_user/login_auth0.html
flask_user/templates/flask_user/login_or_register.html
flask_user/templates/flask_user/manage_emails.html
flask_user/templates/flask_user/register.html
flask_user/templates/flask_user/resend_confirm_email.html
flask_user/templates/flask_user/reset_password.html
flask_user/templates/flask_user/emails/base_message.html
flask_user/templates/flask_user/emails/base_message.txt
